resopath/__init__.py
resopath/cli.py
resopath/env.py
resopath/resolver.py
resopath-0.1.0.dist-info/licenses/LICENSE
resopath-0.1.0.dist-info/METADATA
resopath-0.1.0.dist-info/WHEEL
resopath-0.1.0.dist-info/entry_points.txt
resopath-0.1.0.dist-info/top_level.txt
resopath-0.1.0.dist-info/RECORD
